mad_monkey/__init__.py
mad_monkey/main.py
mad_monkey-0.2.0.dist-info/entry_points.txt
mad_monkey-0.2.0.dist-info/WHEEL
mad_monkey-0.2.0.dist-info/METADATA
mad_monkey-0.2.0.dist-info/RECORD
