Metadata-Version: 2.1
Name: mad-monkey
Version: 0.2.0
Summary: 
Author: Aadityansha
Requires-Python: >=3.10,<4.0
Classifier: Programming Language :: Python :: 3
Classifier: Programming Language :: Python :: 3.10
Requires-Dist: typer[all] (>=0.6.1,<0.7.0)
